<?xml version="1.0" ?><files><file><title>Les plantes</title><author>Ferran Estruch Mascarell</author><area>Ciències experimentals</area><language>Català (ca)</language><file_name>plantes2.jclic.zip</file_name></file><file><title>Sistema Solar</title><author>Francisco Sancho Bautista i José Gallardo Vigil</author><area>Ciències experimentals</area><language>Castellano</language><file_name>ssolar.jclic.zip</file_name></file><file><title>Sistema binario</title><author>Félix Manuel Redondo Templado</author><area>Tecnología</area><language>Castellano</language><file_name>binario.jclic.zip</file_name></file><file><title>Coloraines</title><author>Yolanda Hidalgo López</author><area>Diversos</area><language>Català(ca)</language><file_name>colorain.jclic.zip</file_name></file><file><title>Bugs</title><author>Monica Bayetto Lechuga</author><area>Lenguas</area><language>English</language><file_name>bugs.jclic.zip</file_name></file><file><title>Hergé - Tintín</title><author>Anna Boix i Moradell</author><area>Llengues</area><language>Català (ca)</language><file_name>herge2.jclic.zip</file_name></file><file><title>El conill</title><author>Silvia Puig</author><area>Llengues</area><language>Català (ca)</language><file_name>conill.jclic.zip</file_name></file></files>